rusn/__init__.py
rusn-1.0.1.dist-info/LICENSE
rusn-1.0.1.dist-info/METADATA
rusn-1.0.1.dist-info/WHEEL
rusn-1.0.1.dist-info/top_level.txt
rusn-1.0.1.dist-info/RECORD
