Metadata-Version: 2.1
Name: rusn
Version: 1.0.1
Summary: Small library for getting russian text with singular and plural forms
Home-page: UNKNOWN
Author: Dmitriy Pleshevskiy
Author-email: dmitriy@ideascup.me
License: MIT
Platform: UNKNOWN
